gmail_sms/__init__.py
gmail_sms/gmail.py
gmail_sms-0.0.5.dist-info/METADATA
gmail_sms-0.0.5.dist-info/WHEEL
gmail_sms-0.0.5.dist-info/licenses/LICENSE
gmail_sms-0.0.5.dist-info/RECORD
