Metadata-Version: 2.1
Name: gmail_sms
Version: 0.0.5
Summary: This is gmail_sms package used for sending emails to single as well as multiple users
Project-URL: Homepage, https://github.com/esraldesta/gmail_sms
Project-URL: Bug Tracker, https://github.com/pypa/sampleproject/issues
Author-email: Esral Desta <esraldesta@gmail.com>
License-File: LICENSE
Classifier: License :: OSI Approved :: MIT License
Classifier: Operating System :: OS Independent
Classifier: Programming Language :: Python :: 3
Requires-Python: >=3.7
